missing_values_101703382/__init__.py
missing_values_101703382/missing_values.py
missing_values_101703382-0.0.1.dist-info/LICENSE.txt
missing_values_101703382-0.0.1.dist-info/METADATA
missing_values_101703382-0.0.1.dist-info/WHEEL
missing_values_101703382-0.0.1.dist-info/top_level.txt
missing_values_101703382-0.0.1.dist-info/RECORD
