Metadata-Version: 2.1
Name: missing-values-101703382
Version: 0.0.1
Summary: Technique for filling Missing values
Home-page: UNKNOWN
Author: Paras Arora
Author-email: parora_be17@thapar.edu
License: UNKNOWN
Platform: UNKNOWN
Classifier: Programming Language :: Python :: 3
Classifier: License :: OSI Approved :: MIT License
Classifier: Operating System :: OS Independent
Requires-Python: >=3.7
